conncomb/__init__.py
conncomb/combinatorialanalysis.py
conncomb/genebased.py
conncomb/geneidmatching.py
conncomb/patientbased.py
conncomb/randomconnectivity.py
conncomb/recongraph.py
conncomb-0.0.6.dist-info/LICENCE.txt
conncomb-0.0.6.dist-info/METADATA
conncomb-0.0.6.dist-info/WHEEL
conncomb-0.0.6.dist-info/top_level.txt
conncomb-0.0.6.dist-info/RECORD
