Metadata-Version: 2.1
Name: conncomb
Version: 0.0.6
Summary: connectivity and combinatorial analysis
Author-email: Eda Cakir <e.cakir@jacobs-university.de>
Classifier: Programming Language :: Python :: 3
Classifier: License :: OSI Approved :: MIT License
Classifier: Operating System :: OS Independent
Requires-Python: >=3.7
License-File: LICENCE.txt
